journalparse.py
journalparse-0.1.1.dist-info/DESCRIPTION.rst
journalparse-0.1.1.dist-info/METADATA
journalparse-0.1.1.dist-info/RECORD
journalparse-0.1.1.dist-info/WHEEL
journalparse-0.1.1.dist-info/metadata.json
journalparse-0.1.1.dist-info/top_level.txt
