Metadata-Version: 2.0
Name: journalparse
Version: 0.1.1
Summary: A Python parser for the journald binary export format
Home-page: https://github.com/jbg/journalparse
Author: Jasper Bryant-Greene
Author-email: jbg@rf.net.nz
License: MIT
Keywords: logging journald
Platform: UNKNOWN
Classifier: Development Status :: 3 - Alpha
Classifier: Intended Audience :: Developers
Classifier: Intended Audience :: System Administrators
Classifier: Topic :: System :: Logging
Classifier: License :: OSI Approved :: MIT License
Classifier: Programming Language :: Python :: 2
Classifier: Programming Language :: Python :: 2.6
Classifier: Programming Language :: Python :: 2.7
Classifier: Programming Language :: Python :: 3
Classifier: Programming Language :: Python :: 3.2
Classifier: Programming Language :: Python :: 3.3
Classifier: Programming Language :: Python :: 3.4
Classifier: Programming Language :: Python :: 3.5
